anthrosolui/__init__.py
anthrosolui/_modidx.py
anthrosolui/all.py
anthrosolui/core.py
anthrosolui/daisy.py
anthrosolui/foundations.py
anthrosolui/franken.py
anthrosolui/streaming.py
anthrosolui-0.1.24.dist-info/LICENSE
anthrosolui-0.1.24.dist-info/METADATA
anthrosolui-0.1.24.dist-info/WHEEL
anthrosolui-0.1.24.dist-info/entry_points.txt
anthrosolui-0.1.24.dist-info/top_level.txt
anthrosolui-0.1.24.dist-info/RECORD
