Metadata-Version: 2.2
Name: anthrosolui
Version: 0.1.24
Summary: UI component library built on FastHTML, MonsterUI Tailwind, and DaisyUI
Home-page: https://github.com/breytenlybaert/AnthrosolUI
Author: Breyten Lybaert
Author-email: breyten@anthrosol.com
License: Apache Software License 2.0
Keywords: nbdev jupyter notebook python ui components
Classifier: Development Status :: 4 - Beta
Classifier: Intended Audience :: Developers
Classifier: Natural Language :: English
Classifier: Programming Language :: Python :: 3.10
Classifier: License :: OSI Approved :: Apache Software License
Requires-Python: >=3.10
License-File: LICENSE
Provides-Extra: dev
Dynamic: author
Dynamic: author-email
Dynamic: classifier
Dynamic: description
Dynamic: description-content-type
Dynamic: home-page
Dynamic: keywords
Dynamic: license
Dynamic: provides-extra
Dynamic: requires-python
Dynamic: summary
